color_palette_cli
