Metadata-Version: 2.1
Name: color-palette-cli
Version: 0.1.15
Summary: Command Line Interface allowing interaction with color_palette_at library.
Home-page: UNKNOWN
Author: Adam T
Author-email: adam.tabaczynski@bitcomp.fi
License: MIT
Keywords: color color_palette colors cli
Platform: UNKNOWN
Classifier: Programming Language :: Python :: 3.7
Classifier: Development Status :: 3 - Alpha
Classifier: Topic :: Utilities
Classifier: License :: OSI Approved :: MIT License
Requires-Python: >=3.7
License-File: LICENSE.txt
